README.rst
setup.py
pdir/__init__.py
pdir.egg-info/PKG-INFO
pdir.egg-info/SOURCES.txt
pdir.egg-info/dependency_links.txt
pdir.egg-info/top_level.txt