Metadata-Version: 1.1
Name: pdir
Version: 0.2.2
Summary: A Selective,Pretty dir printing utility for Python.
Home-page: https://github.com/pramttl/pdir
Author: Pranjal Mittal
Author-email: pranjal.mittal.ece10@iitbhu.ac.in
License: BSD
Keywords: regex dir pretty namespaces
Platform: UNKNOWN
Classifier: Intended Audience :: Developers
Classifier: Development Status :: 4 - Beta
Classifier: Programming Language :: Python :: 2
